{
  "name": "RandomForestClassifier Example Dashboard.",
  "description": null,
  "permissions": "PUBLIC_READ_WRITE",
  "pages": [
    {
      "name": "Inference_Data",
      "description": null,
      "widgets": [
        {
          "visualization": {
            "id": "viz.markdown"
          },
          "layout": {
            "column": 1,
            "row": 1,
            "height": 3,
            "width": 4
          },
          "title": "",
          "rawConfiguration": {
            "text": "# ML Monitoring - Bring Your Own Data\n## Example Dashboard\n\n\nThis is an example dashboard displaying metrics and inference data for a RandomForest Classifier model on Iris Dataset.\n\nAfter running the example notebook 'sklearn.RandomForestClassifier_on_Iris_dataset.ipynb' from [here](https://github.com/newrelic-experimental/ml-performance-monitoring/tree/main/examples), and generate some sample data (the last cell of the notebook) you will be able to watch model preformance and data metrics, as well as labels and features distributions."
          },
          "linkedEntityGuids": null
        },
        {
          "visualization": {
            "id": "viz.table"
          },
          "layout": {
            "column": 5,
            "row": 1,
            "height": 3,
            "width": 2
          },
          "title": "Model Features",
          "rawConfiguration": {
            "dataFormatters": [],
            "facet": {
              "showOtherSeries": false
            },
            "nrqlQueries": [
              {
                "query": "SELECT latest(columnType) AS feature_type FROM InferenceData WHERE columnName LIKE 'feature_%' AND columnType IS NOT NULL AND modelName = 'RandomForest Classifier on Iris Dataset - Inference Simulation' FACET capture(columnName, r'feature_(?P<feature>.*)') SINCE 1 month AGO "
              }
            ]
          },
          "linkedEntityGuids": null
        },
        {
          "visualization": {
            "id": "viz.table"
          },
          "layout": {
            "column": 7,
            "row": 1,
            "height": 3,
            "width": 2
          },
          "title": "Model Labels",
          "rawConfiguration": {
            "dataFormatters": [],
            "facet": {
              "showOtherSeries": false
            },
            "nrqlQueries": [
              {
                "accountId": 10538189,
                "query": "SELECT latest(columnType)  AS label_type FROM InferenceData WHERE columnName LIKE 'label_%' AND columnType IS NOT NULL and modelName = 'RandomForest Classifier on Iris Dataset - Inference Simulation' FACET capture(columnName, r'label_(?P<label>.*)') SINCE 1 month AGO "
              }
            ]
          },
          "linkedEntityGuids": null
        },
        {
          "visualization": {
            "id": "viz.pie"
          },
          "layout": {
            "column": 9,
            "row": 1,
            "height": 3,
            "width": 4
          },
          "title": "Label Distribution",
          "rawConfiguration": {
            "facet": {
              "showOtherSeries": false
            },
            "nrqlQueries": [
              {
                "accountId": 10538189,
                "query": "SELECT count(*) FROM InferenceData WHERE label_species IS NOT NULL and modelName = 'RandomForest Classifier on Iris Dataset - Inference Simulation' FACET label_species"
              }
            ]
          },
          "linkedEntityGuids": null
        },
        {
          "visualization": {
            "id": "viz.table"
          },
          "layout": {
            "column": 1,
            "row": 4,
            "height": 3,
            "width": 12
          },
          "title": "Inference Data Sample  ",
          "rawConfiguration": {
            "dataFormatters": [],
            "facet": {
              "showOtherSeries": false
            },
            "nrqlQueries": [
              {
                "accountId": 10538189,
                "query": "SELECT timestamp, modelName, dataset, index, feature_petal_length, feature_petal_width, feature_sepal_length, feature_sepal_width, label_species FROM InferenceData WHERE columnName IS NULL and modelName='RandomForest Classifier on Iris Dataset - Inference Simulation' limit 50"
              }
            ]
          },
          "linkedEntityGuids": null
        },
        {
          "visualization": {
            "id": "viz.markdown"
          },
          "layout": {
            "column": 1,
            "row": 7,
            "height": 1,
            "width": 12
          },
          "title": "",
          "rawConfiguration": {
            "text": "# Model Performance Metrics"
          },
          "linkedEntityGuids": null
        },
        {
          "visualization": {
            "id": "viz.line"
          },
          "layout": {
            "column": 1,
            "row": 8,
            "height": 2,
            "width": 3
          },
          "title": "Accuracy",
          "rawConfiguration": {
            "dataFormatters": [],
            "facet": {
              "showOtherSeries": false
            },
            "legend": {
              "enabled": true
            },
            "nrqlQueries": [
              {
                "accountId": 10538189,
                "query": "SELECT sum(Accuracy)  AS 'Accuracy' FROM Metric WHERE modelName='RandomForest Classifier on Iris Dataset - Inference Simulation' TIMESERIES "
              }
            ],
            "yAxisLeft": {
              "zero": true
            }
          },
          "linkedEntityGuids": null
        },
        {
          "visualization": {
            "id": "viz.line"
          },
          "layout": {
            "column": 4,
            "row": 8,
            "height": 2,
            "width": 3
          },
          "title": "Precision",
          "rawConfiguration": {
            "dataFormatters": [],
            "facet": {
              "showOtherSeries": false
            },
            "legend": {
              "enabled": true
            },
            "nrqlQueries": [
              {
                "accountId": 10538189,
                "query": "SELECT sum(Precision)  AS 'Precision' FROM Metric WHERE modelName='RandomForest Classifier on Iris Dataset - Inference Simulation' TIMESERIES "
              }
            ],
            "yAxisLeft": {
              "zero": true
            }
          },
          "linkedEntityGuids": null
        },
        {
          "visualization": {
            "id": "viz.line"
          },
          "layout": {
            "column": 7,
            "row": 8,
            "height": 2,
            "width": 3
          },
          "title": "Recall",
          "rawConfiguration": {
            "dataFormatters": [],
            "facet": {
              "showOtherSeries": false
            },
            "legend": {
              "enabled": true
            },
            "nrqlQueries": [
              {
                "accountId": 10538189,
                "query": "SELECT sum(Recall)  AS 'Recall' FROM Metric WHERE modelName='RandomForest Classifier on Iris Dataset - Inference Simulation' TIMESERIES "
              }
            ],
            "yAxisLeft": {
              "zero": true
            }
          },
          "linkedEntityGuids": null
        },
        {
          "visualization": {
            "id": "viz.line"
          },
          "layout": {
            "column": 10,
            "row": 8,
            "height": 2,
            "width": 3
          },
          "title": "F1 Score",
          "rawConfiguration": {
            "dataFormatters": [],
            "facet": {
              "showOtherSeries": false
            },
            "legend": {
              "enabled": true
            },
            "nrqlQueries": [
              {
                "accountId": 10538189,
                "query": "SELECT sum(`F1_Score`)  FROM Metric WHERE modelName='RandomForest Classifier on Iris Dataset - Inference Simulation'  TIMESERIES"
              }
            ],
            "yAxisLeft": {
              "zero": true
            }
          },
          "linkedEntityGuids": null
        },
        {
          "visualization": {
            "id": "viz.markdown"
          },
          "layout": {
            "column": 1,
            "row": 10,
            "height": 1,
            "width": 12
          },
          "title": "",
          "rawConfiguration": {
            "text": "# Data Metrics and Feature Distributions"
          },
          "linkedEntityGuids": null
        },
        {
          "visualization": {
            "id": "viz.markdown"
          },
          "layout": {
            "column": 1,
            "row": 11,
            "height": 1,
            "width": 12
          },
          "title": "",
          "rawConfiguration": {
            "text": "sepal_width"
          },
          "linkedEntityGuids": null
        },
        {
          "visualization": {
            "id": "viz.line"
          },
          "layout": {
            "column": 1,
            "row": 12,
            "height": 3,
            "width": 2
          },
          "title": "Count",
          "rawConfiguration": {
            "legend": {
              "enabled": true
            },
            "nrqlQueries": [
              {
                "accountId": 10538189,
                "query": "SELECT count(feature_sepal_width) AS 'count' FROM InferenceData WHERE modelName='RandomForest Classifier on Iris Dataset - Inference Simulation' LIMIT MAX TIMESERIES "
              }
            ],
            "yAxisLeft": {
              "zero": true
            }
          },
          "linkedEntityGuids": null
        },
        {
          "visualization": {
            "id": "viz.line"
          },
          "layout": {
            "column": 3,
            "row": 12,
            "height": 3,
            "width": 2
          },
          "title": "Missing Values",
          "rawConfiguration": {
            "dataFormatters": [],
            "facet": {
              "showOtherSeries": false
            },
            "legend": {
              "enabled": true
            },
            "nrqlQueries": [
              {
                "accountId": 10538189,
                "query": "SELECT count(feature_sepal_width) AS 'missing values' FROM InferenceData WHERE modelName='RandomForest Classifier on Iris Dataset - Inference Simulation' AND feature_sepal_width IS NULL AND columnName IS NULL LIMIT MAX TIMESERIES "
              }
            ],
            "yAxisLeft": {
              "zero": true
            }
          },
          "linkedEntityGuids": null
        },
        {
          "visualization": {
            "id": "viz.line"
          },
          "layout": {
            "column": 5,
            "row": 12,
            "height": 3,
            "width": 2
          },
          "title": "Min, Average, Max",
          "rawConfiguration": {
            "dataFormatters": [],
            "facet": {
              "showOtherSeries": false
            },
            "legend": {
              "enabled": true
            },
            "nrqlQueries": [
              {
                "accountId": 10538189,
                "query": "SELECT min(feature_sepal_width) as min, average(feature_sepal_width) as average, max(feature_sepal_width) as max FROM InferenceData WHERE modelName='RandomForest Classifier on Iris Dataset - Inference Simulation' LIMIT MAX TIMESERIES "
              }
            ],
            "yAxisLeft": {
              "zero": true
            }
          },
          "linkedEntityGuids": null
        },
        {
          "visualization": {
            "id": "viz.line"
          },
          "layout": {
            "column": 7,
            "row": 12,
            "height": 3,
            "width": 2
          },
          "title": "Percentile",
          "rawConfiguration": {
            "legend": {
              "enabled": true
            },
            "nrqlQueries": [
              {
                "accountId": 10538189,
                "query": "SELECT percentile(feature_sepal_width, 25, 50, 75) FROM InferenceData WHERE modelName='RandomForest Classifier on Iris Dataset - Inference Simulation' LIMIT MAX TIMESERIES"
              }
            ],
            "yAxisLeft": {
              "zero": true
            }
          },
          "linkedEntityGuids": null
        },
        {
          "visualization": {
            "id": "viz.line"
          },
          "layout": {
            "column": 9,
            "row": 12,
            "height": 3,
            "width": 2
          },
          "title": "Standard deviation",
          "rawConfiguration": {
            "legend": {
              "enabled": true
            },
            "nrqlQueries": [
              {
                "accountId": 10538189,
                "query": "SELECT stddev(feature_sepal_width) FROM InferenceData WHERE modelName='RandomForest Classifier on Iris Dataset - Inference Simulation' LIMIT MAX TIMESERIES"
              }
            ],
            "yAxisLeft": {
              "zero": true
            }
          },
          "linkedEntityGuids": null
        },
        {
          "visualization": {
            "id": "viz.histogram"
          },
          "layout": {
            "column": 11,
            "row": 12,
            "height": 3,
            "width": 2
          },
          "title": "Feature Distribution",
          "rawConfiguration": {
            "legend": {
              "enabled": true
            },
            "nrqlQueries": [
              {
                "accountId": 10538189,
                "query": "SELECT histogram(feature_sepal_width) FROM InferenceData WHERE modelName='RandomForest Classifier on Iris Dataset - Inference Simulation' LIMIT MAX"
              }
            ]
          },
          "linkedEntityGuids": null
        },
        {
          "visualization": {
            "id": "viz.markdown"
          },
          "layout": {
            "column": 1,
            "row": 15,
            "height": 1,
            "width": 12
          },
          "title": "",
          "rawConfiguration": {
            "text": "petal_width"
          },
          "linkedEntityGuids": null
        },
        {
          "visualization": {
            "id": "viz.line"
          },
          "layout": {
            "column": 1,
            "row": 16,
            "height": 3,
            "width": 2
          },
          "title": "Count",
          "rawConfiguration": {
            "legend": {
              "enabled": true
            },
            "nrqlQueries": [
              {
                "accountId": 10538189,
                "query": "SELECT count(feature_petal_width) AS 'count' FROM InferenceData WHERE modelName='RandomForest Classifier on Iris Dataset - Inference Simulation' LIMIT MAX TIMESERIES "
              }
            ],
            "yAxisLeft": {
              "zero": true
            }
          },
          "linkedEntityGuids": null
        },
        {
          "visualization": {
            "id": "viz.line"
          },
          "layout": {
            "column": 3,
            "row": 16,
            "height": 3,
            "width": 2
          },
          "title": "Missing Values",
          "rawConfiguration": {
            "dataFormatters": [],
            "facet": {
              "showOtherSeries": false
            },
            "legend": {
              "enabled": true
            },
            "nrqlQueries": [
              {
                "accountId": 10538189,
                "query": "SELECT count(feature_petal_width) AS 'missing values' FROM InferenceData WHERE modelName='RandomForest Classifier on Iris Dataset - Inference Simulation' AND feature_sepal_width IS NULL AND columnName IS NULL LIMIT MAX TIMESERIES "
              }
            ],
            "yAxisLeft": {
              "zero": true
            }
          },
          "linkedEntityGuids": null
        },
        {
          "visualization": {
            "id": "viz.line"
          },
          "layout": {
            "column": 5,
            "row": 16,
            "height": 3,
            "width": 2
          },
          "title": "Min, Average, Max",
          "rawConfiguration": {
            "dataFormatters": [],
            "facet": {
              "showOtherSeries": false
            },
            "legend": {
              "enabled": true
            },
            "nrqlQueries": [
              {
                "accountId": 10538189,
                "query": "SELECT min(feature_petal_width) as min, average(feature_petal_width) as average, max(feature_petal_width) AS max FROM InferenceData WHERE modelName='RandomForest Classifier on Iris Dataset - Inference Simulation' LIMIT MAX TIMESERIES "
              }
            ],
            "yAxisLeft": {
              "zero": true
            }
          },
          "linkedEntityGuids": null
        },
        {
          "visualization": {
            "id": "viz.line"
          },
          "layout": {
            "column": 7,
            "row": 16,
            "height": 3,
            "width": 2
          },
          "title": "Percentile",
          "rawConfiguration": {
            "legend": {
              "enabled": true
            },
            "nrqlQueries": [
              {
                "accountId": 10538189,
                "query": "SELECT percentile(feature_petal_width, 25, 50, 75) FROM InferenceData WHERE modelName='RandomForest Classifier on Iris Dataset - Inference Simulation' LIMIT MAX TIMESERIES"
              }
            ],
            "yAxisLeft": {
              "zero": true
            }
          },
          "linkedEntityGuids": null
        },
        {
          "visualization": {
            "id": "viz.line"
          },
          "layout": {
            "column": 9,
            "row": 16,
            "height": 3,
            "width": 2
          },
          "title": "Standard deviation",
          "rawConfiguration": {
            "legend": {
              "enabled": true
            },
            "nrqlQueries": [
              {
                "accountId": 10538189,
                "query": "SELECT stddev(feature_petal_width) FROM InferenceData WHERE modelName='RandomForest Classifier on Iris Dataset - Inference Simulation' LIMIT MAX TIMESERIES"
              }
            ],
            "yAxisLeft": {
              "zero": true
            }
          },
          "linkedEntityGuids": null
        },
        {
          "visualization": {
            "id": "viz.histogram"
          },
          "layout": {
            "column": 11,
            "row": 16,
            "height": 3,
            "width": 2
          },
          "title": "Feature Distribution",
          "rawConfiguration": {
            "legend": {
              "enabled": true
            },
            "nrqlQueries": [
              {
                "accountId": 10538189,
                "query": "SELECT histogram(feature_petal_width) FROM InferenceData WHERE modelName='RandomForest Classifier on Iris Dataset - Inference Simulation' LIMIT MAX"
              }
            ]
          },
          "linkedEntityGuids": null
        },
        {
          "visualization": {
            "id": "viz.markdown"
          },
          "layout": {
            "column": 1,
            "row": 19,
            "height": 1,
            "width": 12
          },
          "title": "",
          "rawConfiguration": {
            "text": "sepal_length"
          },
          "linkedEntityGuids": null
        },
        {
          "visualization": {
            "id": "viz.line"
          },
          "layout": {
            "column": 1,
            "row": 20,
            "height": 3,
            "width": 2
          },
          "title": "Count",
          "rawConfiguration": {
            "legend": {
              "enabled": true
            },
            "nrqlQueries": [
              {
                "accountId": 10538189,
                "query": "SELECT count(feature_sepal_length) AS 'count' FROM InferenceData WHERE modelName='RandomForest Classifier on Iris Dataset - Inference Simulation' LIMIT MAX TIMESERIES "
              }
            ],
            "yAxisLeft": {
              "zero": true
            }
          },
          "linkedEntityGuids": null
        },
        {
          "visualization": {
            "id": "viz.line"
          },
          "layout": {
            "column": 3,
            "row": 20,
            "height": 3,
            "width": 2
          },
          "title": "Missing Values",
          "rawConfiguration": {
            "dataFormatters": [],
            "facet": {
              "showOtherSeries": false
            },
            "legend": {
              "enabled": true
            },
            "nrqlQueries": [
              {
                "accountId": 10538189,
                "query": "SELECT count(feature_sepal_length) AS 'missing values' FROM InferenceData WHERE modelName='RandomForest Classifier on Iris Dataset - Inference Simulation' AND feature_sepal_length IS NULL AND columnName IS NULL LIMIT MAX TIMESERIES "
              }
            ],
            "yAxisLeft": {
              "zero": true
            }
          },
          "linkedEntityGuids": null
        },
        {
          "visualization": {
            "id": "viz.line"
          },
          "layout": {
            "column": 5,
            "row": 20,
            "height": 3,
            "width": 2
          },
          "title": "Min, Average, Max",
          "rawConfiguration": {
            "dataFormatters": [],
            "facet": {
              "showOtherSeries": false
            },
            "legend": {
              "enabled": true
            },
            "nrqlQueries": [
              {
                "accountId": 10538189,
                "query": "SELECT min(feature_sepal_length) as min, average(feature_sepal_length) as average, max(feature_sepal_length) as max FROM InferenceData WHERE modelName='RandomForest Classifier on Iris Dataset - Inference Simulation' LIMIT MAX TIMESERIES "
              }
            ],
            "yAxisLeft": {
              "zero": true
            }
          },
          "linkedEntityGuids": null
        },
        {
          "visualization": {
            "id": "viz.line"
          },
          "layout": {
            "column": 7,
            "row": 20,
            "height": 3,
            "width": 2
          },
          "title": "Percentile",
          "rawConfiguration": {
            "legend": {
              "enabled": true
            },
            "nrqlQueries": [
              {
                "accountId": 10538189,
                "query": "SELECT percentile(feature_sepal_length, 25, 50, 75) FROM InferenceData WHERE modelName='RandomForest Classifier on Iris Dataset - Inference Simulation' LIMIT MAX TIMESERIES"
              }
            ],
            "yAxisLeft": {
              "zero": true
            }
          },
          "linkedEntityGuids": null
        },
        {
          "visualization": {
            "id": "viz.line"
          },
          "layout": {
            "column": 9,
            "row": 20,
            "height": 3,
            "width": 2
          },
          "title": "Standard deviation",
          "rawConfiguration": {
            "legend": {
              "enabled": true
            },
            "nrqlQueries": [
              {
                "accountId": 10538189,
                "query": "SELECT stddev(feature_sepal_length) FROM InferenceData WHERE modelName='RandomForest Classifier on Iris Dataset - Inference Simulation' LIMIT MAX TIMESERIES"
              }
            ],
            "yAxisLeft": {
              "zero": true
            }
          },
          "linkedEntityGuids": null
        },
        {
          "visualization": {
            "id": "viz.histogram"
          },
          "layout": {
            "column": 11,
            "row": 20,
            "height": 3,
            "width": 2
          },
          "title": "Feature Distribution",
          "rawConfiguration": {
            "legend": {
              "enabled": true
            },
            "nrqlQueries": [
              {
                "accountId": 10538189,
                "query": "SELECT histogram(feature_sepal_length) FROM InferenceData WHERE modelName='RandomForest Classifier on Iris Dataset - Inference Simulation' LIMIT MAX"
              }
            ]
          },
          "linkedEntityGuids": null
        },
        {
          "visualization": {
            "id": "viz.markdown"
          },
          "layout": {
            "column": 1,
            "row": 23,
            "height": 1,
            "width": 12
          },
          "title": "",
          "rawConfiguration": {
            "text": "Petal length\n\n\n\n"
          },
          "linkedEntityGuids": null
        },
        {
          "visualization": {
            "id": "viz.line"
          },
          "layout": {
            "column": 1,
            "row": 24,
            "height": 3,
            "width": 2
          },
          "title": "count",
          "rawConfiguration": {
            "legend": {
              "enabled": true
            },
            "nrqlQueries": [
              {
                "accountId": 10538189,
                "query": "SELECT count(feature_petal_length) AS 'count' FROM InferenceData WHERE modelName='RandomForest Classifier on Iris Dataset - Inference Simulation' LIMIT MAX TIMESERIES "
              }
            ],
            "yAxisLeft": {
              "zero": true
            }
          },
          "linkedEntityGuids": null
        },
        {
          "visualization": {
            "id": "viz.line"
          },
          "layout": {
            "column": 3,
            "row": 24,
            "height": 3,
            "width": 2
          },
          "title": "Missing Values",
          "rawConfiguration": {
            "dataFormatters": [],
            "facet": {
              "showOtherSeries": false
            },
            "legend": {
              "enabled": true
            },
            "nrqlQueries": [
              {
                "accountId": 10538189,
                "query": "SELECT count(feature_petal_length) AS 'missing values' FROM InferenceData WHERE modelName='RandomForest Classifier on Iris Dataset - Inference Simulation' AND feature_sepal_length IS NULL AND columnName IS NULL LIMIT MAX TIMESERIES "
              }
            ],
            "yAxisLeft": {
              "zero": true
            }
          },
          "linkedEntityGuids": null
        },
        {
          "visualization": {
            "id": "viz.line"
          },
          "layout": {
            "column": 5,
            "row": 24,
            "height": 3,
            "width": 2
          },
          "title": "Min, Average, Max",
          "rawConfiguration": {
            "dataFormatters": [],
            "facet": {
              "showOtherSeries": false
            },
            "legend": {
              "enabled": true
            },
            "nrqlQueries": [
              {
                "accountId": 10538189,
                "query": "SELECT min(feature_sepal_length) AS min, average(feature_sepal_length) AS average, max(feature_sepal_length) AS max FROM InferenceData WHERE modelName='RandomForest Classifier on Iris Dataset - Inference Simulation' LIMIT MAX TIMESERIES "
              }
            ],
            "yAxisLeft": {
              "zero": true
            }
          },
          "linkedEntityGuids": null
        },
        {
          "visualization": {
            "id": "viz.line"
          },
          "layout": {
            "column": 7,
            "row": 24,
            "height": 3,
            "width": 2
          },
          "title": "Percentile",
          "rawConfiguration": {
            "legend": {
              "enabled": true
            },
            "nrqlQueries": [
              {
                "accountId": 10538189,
                "query": "SELECT percentile(feature_petal_length, 25, 50, 75) FROM InferenceData WHERE modelName='RandomForest Classifier on Iris Dataset - Inference Simulation' LIMIT MAX TIMESERIES"
              }
            ],
            "yAxisLeft": {
              "zero": true
            }
          },
          "linkedEntityGuids": null
        },
        {
          "visualization": {
            "id": "viz.line"
          },
          "layout": {
            "column": 9,
            "row": 24,
            "height": 3,
            "width": 2
          },
          "title": "Standard deviation",
          "rawConfiguration": {
            "legend": {
              "enabled": true
            },
            "nrqlQueries": [
              {
                "accountId": 10538189,
                "query": "SELECT stddev(feature_petal_length) FROM InferenceData WHERE modelName='RandomForest Classifier on Iris Dataset - Inference Simulation' LIMIT MAX TIMESERIES"
              }
            ],
            "yAxisLeft": {
              "zero": true
            }
          },
          "linkedEntityGuids": null
        },
        {
          "visualization": {
            "id": "viz.histogram"
          },
          "layout": {
            "column": 11,
            "row": 24,
            "height": 3,
            "width": 2
          },
          "title": "Feature Distribution",
          "rawConfiguration": {
            "legend": {
              "enabled": true
            },
            "nrqlQueries": [
              {
                "accountId": 10538189,
                "query": "SELECT histogram(feature_petal_length) FROM InferenceData WHERE modelName='RandomForest Classifier on Iris Dataset - Inference Simulation' LIMIT MAX"
              }
            ]
          },
          "linkedEntityGuids": null
        }
      ]
    }
  ]
}
